{
  "department": "33",
  "updateDate": "2025-09-11T05:22:21.889Z",
  "dateRange": "2022-09-11 to present",
  "surfaceRanges": [
    {
      "range": "15-35m²",
      "count": 39189,
      "avgSurface": 25,
      "consumption": {
        "total": 242,
        "chauffage": 123,
        "eau_chaude": 101
      },
      "ges": 17,
      "acPercentage": 3
    },
    {
      "range": "36-60m²",
      "count": 63059,
      "avgSurface": 48,
      "consumption": {
        "total": 188,
        "chauffage": 113,
        "eau_chaude": 58
      },
      "ges": 18,
      "acPercentage": 4
    },
    {
      "range": "61-90m²",
      "count": 96734,
      "avgSurface": 74,
      "consumption": {
        "total": 168,
        "chauffage": 111,
        "eau_chaude": 39
      },
      "ges": 21,
      "acPercentage": 5
    },
    {
      "range": "91-150m²",
      "count": 42728,
      "avgSurface": 112,
      "consumption": {
        "total": 185,
        "chauffage": 140,
        "eau_chaude": 30
      },
      "ges": 21,
      "acPercentage": 21
    },
    {
      "range": "151-250m²",
      "count": 10710,
      "avgSurface": 183,
      "consumption": {
        "total": 181,
        "chauffage": 146,
        "eau_chaude": 23
      },
      "ges": 23,
      "acPercentage": 29
    },
    {
      "range": "250m²+",
      "count": 1822,
      "avgSurface": 314,
      "consumption": {
        "total": 183,
        "chauffage": 155,
        "eau_chaude": 19
      },
      "ges": 28,
      "acPercentage": 29
    }
  ],
  "overall": {
    "range": "all",
    "count": 262482,
    "avgSurface": 72,
    "consumption": {
      "total": 181,
      "chauffage": 125,
      "eau_chaude": 41
    },
    "ges": 21,
    "acPercentage": 8
  }
}
